check_mk_web_api/__init__.py
check_mk_web_api/exception.py
check_mk_web_api/test_WebApi.py
check_mk_web_api-1.9.0.dist-info/LICENSE
check_mk_web_api-1.9.0.dist-info/METADATA
check_mk_web_api-1.9.0.dist-info/WHEEL
check_mk_web_api-1.9.0.dist-info/top_level.txt
check_mk_web_api-1.9.0.dist-info/RECORD
