Metadata-Version: 2.1
Name: check-mk-web-api
Version: 1.9.0
Summary: Library to talk to Check_Mk Web API
Home-page: https://github.com/brennerm/check-mk-web-api
Author: Max Brenner
Author-email: xamrennerb@gmail.com
License: UNKNOWN
Download-URL: https://github.com/brennerm/check-mk-web-api/archive/1.9.0.tar.gz
Keywords: check_mk,api,monitoring
Platform: UNKNOWN
Requires-Dist: six
Requires-Dist: enum34 ; python_version < "3.4"
